production_rag/__init__.py
production_rag/cache.py
production_rag/chunker.py
production_rag/embedder.py
production_rag/generator.py
production_rag/pipeline.py
production_rag/reranker.py
production_rag/retriever.py
production_rag/types.py
production_rag/vectorstore.py
production_rag-1.0.0.dist-info/licenses/LICENSE
production_rag-1.0.0.dist-info/METADATA
production_rag-1.0.0.dist-info/WHEEL
production_rag-1.0.0.dist-info/top_level.txt
production_rag-1.0.0.dist-info/RECORD
