Metadata-Version: 2.4
Name: production-rag
Version: 1.0.0
Summary: Enterprise-ready Retrieval-Augmented Generation framework with superior performance, reliability, and observability
Author-email: Pranay M <pranay@example.com>
Maintainer-email: Pranay M <pranay@example.com>
License: MIT
Project-URL: Homepage, https://github.com/pranaym/production-rag
Project-URL: Documentation, https://github.com/pranaym/production-rag#readme
Project-URL: Repository, https://github.com/pranaym/production-rag
Project-URL: Issues, https://github.com/pranaym/production-rag/issues
Project-URL: Changelog, https://github.com/pranaym/production-rag/blob/main/CHANGELOG.md
Keywords: rag,retrieval-augmented-generation,llm,ai,nlp,vector-search,embeddings,semantic-search,document-retrieval,question-answering,chatbot,enterprise,production
Classifier: Development Status :: 5 - Production/Stable
Classifier: Intended Audience :: Developers
Classifier: Intended Audience :: Science/Research
Classifier: License :: OSI Approved :: MIT License
Classifier: Operating System :: OS Independent
Classifier: Programming Language :: Python :: 3
Classifier: Programming Language :: Python :: 3.8
Classifier: Programming Language :: Python :: 3.9
Classifier: Programming Language :: Python :: 3.10
Classifier: Programming Language :: Python :: 3.11
Classifier: Programming Language :: Python :: 3.12
Classifier: Topic :: Scientific/Engineering :: Artificial Intelligence
Classifier: Topic :: Software Development :: Libraries :: Python Modules
Classifier: Topic :: Text Processing :: Indexing
Classifier: Typing :: Typed
Requires-Python: >=3.8
License-File: LICENSE
Requires-Dist: numpy>=1.20.0
Provides-Extra: embeddings
Requires-Dist: sentence-transformers>=2.2.0; extra == "embeddings"
Requires-Dist: torch>=1.9.0; extra == "embeddings"
Provides-Extra: openai
Requires-Dist: openai>=1.0.0; extra == "openai"
Provides-Extra: anthropic
Requires-Dist: anthropic>=0.18.0; extra == "anthropic"
Provides-Extra: pdf
Requires-Dist: pypdf>=3.0.0; extra == "pdf"
Requires-Dist: pdfplumber>=0.9.0; extra == "pdf"
Provides-Extra: docx
Requires-Dist: python-docx>=0.8.11; extra == "docx"
Provides-Extra: html
Requires-Dist: beautifulsoup4>=4.9.0; extra == "html"
Requires-Dist: lxml>=4.6.0; extra == "html"
Provides-Extra: all
Requires-Dist: sentence-transformers>=2.2.0; extra == "all"
Requires-Dist: torch>=1.9.0; extra == "all"
Requires-Dist: openai>=1.0.0; extra == "all"
Requires-Dist: anthropic>=0.18.0; extra == "all"
Requires-Dist: pypdf>=3.0.0; extra == "all"
Requires-Dist: pdfplumber>=0.9.0; extra == "all"
Requires-Dist: python-docx>=0.8.11; extra == "all"
Requires-Dist: beautifulsoup4>=4.9.0; extra == "all"
Requires-Dist: lxml>=4.6.0; extra == "all"
Requires-Dist: faiss-cpu>=1.7.0; extra == "all"
Requires-Dist: chromadb>=0.4.0; extra == "all"
Provides-Extra: dev
Requires-Dist: pytest>=7.0.0; extra == "dev"
Requires-Dist: pytest-asyncio>=0.21.0; extra == "dev"
Requires-Dist: pytest-cov>=4.0.0; extra == "dev"
Requires-Dist: black>=23.0.0; extra == "dev"
Requires-Dist: isort>=5.12.0; extra == "dev"
Requires-Dist: mypy>=1.0.0; extra == "dev"
Requires-Dist: ruff>=0.1.0; extra == "dev"
Dynamic: license-file
